libprng/__init__.py
libprng/glibc/__init__.py
libprng/glibc/reentrant.py
libprng/glibc/standard.py
libprng-0.0.1.dist-info/METADATA
libprng-0.0.1.dist-info/WHEEL
libprng-0.0.1.dist-info/licenses/LICENSE-BSD-4-Clause
libprng-0.0.1.dist-info/licenses/LICENSE-LGPL-2.1-or-later
libprng-0.0.1.dist-info/licenses/LICENSE-MIT
libprng-0.0.1.dist-info/RECORD
