Metadata-Version: 2.4
Name: libprng
Version: 0.0.1
Summary: Pseudo-random number generators from across projects
Project-URL: Homepage, https://github.com/Jayson-Fong/libprng
Project-URL: Issues, https://github.com/Jayson-Fong/libprng/issues
Author-email: Jayson Fong <jayson.fong@gatech.edu>
License: LGPL-2.1-or-later
License-File: LICENSE-BSD-4-Clause
License-File: LICENSE-LGPL-2.1-or-later
License-File: LICENSE-MIT
Classifier: Development Status :: 3 - Alpha
Classifier: License :: OSI Approved :: MIT License
Classifier: Operating System :: OS Independent
Classifier: Programming Language :: Python
Classifier: Programming Language :: Python :: 3.9
Classifier: Programming Language :: Python :: 3.11
Classifier: Programming Language :: Python :: 3.12
Classifier: Programming Language :: Python :: 3.13
Classifier: Topic :: System :: Networking
Classifier: Typing :: Typed
Requires-Python: >=3.9
